lambder/__init__.py
lambder/cli.py
lambder/lambder.py
lambder-1.2.2.dist-info/DESCRIPTION.rst
lambder-1.2.2.dist-info/entry_points.txt
lambder-1.2.2.dist-info/METADATA
lambder-1.2.2.dist-info/metadata.json
lambder-1.2.2.dist-info/RECORD
lambder-1.2.2.dist-info/top_level.txt
lambder-1.2.2.dist-info/WHEEL
