Metadata-Version: 2.0
Name: lambder
Version: 1.2.2
Summary: Creates and manages scheduled AWS Lambdas
Home-page: https://github.com/LeafSoftware/python-lambder
Author: Chris Chalfant
Author-email: cchalfant@leafsoftwaresolutions.com
License: MIT
Platform: any
Classifier: Development Status :: 4 - Beta
Classifier: Environment :: Console
Classifier: Intended Audience :: Developers
Classifier: License :: OSI Approved :: MIT License
Classifier: Operating System :: POSIX
Classifier: Operating System :: MacOS
Classifier: Operating System :: Unix
Classifier: Operating System :: Microsoft :: Windows
Classifier: Programming Language :: Python
Classifier: Programming Language :: Python :: 2
Classifier: Programming Language :: Python :: 3
Classifier: Topic :: Software Development :: Libraries :: Python Modules
Requires-Dist: click (>=6.2)
Requires-Dist: boto3 (>=1.2.6)
Requires-Dist: botocore (>=1.4.0)
Requires-Dist: cookiecutter (>=1.3.0)
